grabyt/__init__.py
grabyt/cli.py
grabyt-0.1.20.dist-info/METADATA
grabyt-0.1.20.dist-info/WHEEL
grabyt-0.1.20.dist-info/entry_points.txt
grabyt-0.1.20.dist-info/RECORD
